PythonCTP/__init__.py
PythonCTP/thostmduserapi.py
PythonCTP/thosttraderapi.py
PythonCTP-6.3.15.3.dist-info/LICENSE
PythonCTP-6.3.15.3.dist-info/METADATA
PythonCTP-6.3.15.3.dist-info/WHEEL
PythonCTP-6.3.15.3.dist-info/top_level.txt
PythonCTP-6.3.15.3.dist-info/zip-safe
PythonCTP-6.3.15.3.dist-info/RECORD
